ATH/DB_read.py
ATH/DB_send.py
ATH/__init__.py
ATH/abc123_2.py
ATH/arithmetic_average.py
ATH/calculator.py
ATH/env.py
ATH/get_current_time.py
ATH/gmail.py
ATH/owl.py
ATH/qr.py
ATH/safe.py
ATH/scr_shot.py
ATH/scr_shot_telegram.py
ATH/singed.py
ATH/sq_root.py
ATH/telegram.py
ATH/tts.py
ATH/wait.py
ATH/write.py
ATH-0.5.9.dist-info/METADATA
ATH-0.5.9.dist-info/WHEEL
ATH-0.5.9.dist-info/top_level.txt
ATH-0.5.9.dist-info/RECORD
